{
    "AppConfig":{
                    "Vendor":  "Citrix",
                    "Product":  "Workspace",
                    "Version":  "24.5.11.31",
                    "Architecture":  "x64",
                    "InstallBehavior":"system",
                    "DetectionScript": "DetectionScript.ps1",
                    "RequirementScript": "",
                    "Icon":"Citrix-WorkspaceApp.png",
                    "AvailableGroup": "AllDevices",
                    "RequiredGroup": "",
                    "IntuneImport":  "True"
                }
}
